odoo/addons/base_tier_validation_forward/README.rst
odoo/addons/base_tier_validation_forward/__init__.py
odoo/addons/base_tier_validation_forward/__manifest__.py
odoo/addons/base_tier_validation_forward/hooks.py
odoo/addons/base_tier_validation_forward/data/mail_data.xml
odoo/addons/base_tier_validation_forward/i18n/base_tier_validation_forward.pot
odoo/addons/base_tier_validation_forward/i18n/it.po
odoo/addons/base_tier_validation_forward/i18n/zh_CN.po
odoo/addons/base_tier_validation_forward/models/__init__.py
odoo/addons/base_tier_validation_forward/models/tier_definition.py
odoo/addons/base_tier_validation_forward/models/tier_review.py
odoo/addons/base_tier_validation_forward/models/tier_validation.py
odoo/addons/base_tier_validation_forward/readme/CONFIGURE.rst
odoo/addons/base_tier_validation_forward/readme/CONTRIBUTORS.rst
odoo/addons/base_tier_validation_forward/readme/DESCRIPTION.rst
odoo/addons/base_tier_validation_forward/static/description/icon.png
odoo/addons/base_tier_validation_forward/static/description/index.html
odoo/addons/base_tier_validation_forward/static/src/xml/tier_review_template.xml
odoo/addons/base_tier_validation_forward/tests/__init__.py
odoo/addons/base_tier_validation_forward/tests/test_tier_validation.py
odoo/addons/base_tier_validation_forward/tests/tier_validation_tester.py
odoo/addons/base_tier_validation_forward/views/tier_definition_view.xml
odoo/addons/base_tier_validation_forward/wizard/__init__.py
odoo/addons/base_tier_validation_forward/wizard/comment_wizard.py
odoo/addons/base_tier_validation_forward/wizard/forward_wizard.py
odoo/addons/base_tier_validation_forward/wizard/forward_wizard_view.xml
odoo13_addon_base_tier_validation_forward-13.0.1.1.1.dist-info/METADATA
odoo13_addon_base_tier_validation_forward-13.0.1.1.1.dist-info/WHEEL
odoo13_addon_base_tier_validation_forward-13.0.1.1.1.dist-info/top_level.txt
odoo13_addon_base_tier_validation_forward-13.0.1.1.1.dist-info/RECORD
